{
 "kind": "calendar#events",
 "etag": "\"p334r187tkmhuu0g\"",
 "summary": "Hari libur di Indonesia",
 "updated": "2021-03-08T09:02:01.000Z",
 "timeZone": "UTC",
 "accessRole": "reader",
 "defaultReminders": [],
 "nextSyncToken": "CMCozf6qoO8CEAAYASClxf6rAQ==",
 "items": [
  {
   "kind": "calendar#event",
   "etag": "\"3101503503364000\"",
   "id": "20200101_60o30d1pcgo30c1g60o30dr56g",
   "status": "confirmed",
   "htmlLink": "https://www.google.com/calendar/event?eid=MjAyMDAxMDFfNjBvMzBkMXBjZ28zMGMxZzYwbzMwZHI1NmcgaWQuaW5kb25lc2lhbiNob2xpZGF5QHY",
   "created": "2019-02-21T12:22:31.000Z",
   "updated": "2019-02-21T12:22:31.682Z",
   "summary": "Hari Tahun Baru",
   "creator": {
    "email": "id.indonesian#holiday@group.v.calendar.google.com",
    "displayName": "Hari libur di Indonesia",
    "self": true
   },
   "organizer": {
    "email": "id.indonesian#holiday@group.v.calendar.google.com",
    "displayName": "Hari libur di Indonesia",
    "self": true
   },
   "start": {
    "date": "2020-01-01"
   },
   "end": {
    "date": "2020-01-02"
   },
   "transparency": "transparent",
   "visibility": "public",
   "iCalUID": "20200101_60o30d1pcgo30c1g60o30dr56g@google.com",
   "sequence": 0,
   "eventType": "default"
  },
  {
   "kind": "calendar#event",
   "etag": "\"3101503503364000\"",
   "id": "20200125_60o30d326go30c1g60o32chmcg",
   "status": "confirmed",
   "htmlLink": "https://www.google.com/calendar/event?eid=MjAyMDAxMjVfNjBvMzBkMzI2Z28zMGMxZzYwbzMyY2htY2cgaWQuaW5kb25lc2lhbiNob2xpZGF5QHY",
   "created": "2019-02-21T12:22:31.000Z",
   "updated": "2019-02-21T12:22:31.682Z",
   "summary": "Tahun Baru Imlek",
   "creator": {
    "email": "id.indonesian#holiday@group.v.calendar.google.com",
    "displayName": "Hari libur di Indonesia",
    "self": true
   },
   "organizer": {
    "email": "id.indonesian#holiday@group.v.calendar.google.com",
    "displayName": "Hari libur di Indonesia",
    "self": true
   },
   "start": {
    "date": "2020-01-25"
   },
   "end": {
    "date": "2020-01-26"
   },
   "transparency": "transparent",
   "visibility": "public",
   "iCalUID": "20200125_60o30d326go30c1g60o32chmcg@google.com",
   "sequence": 0,
   "eventType": "default"
  },
  {
   "kind": "calendar#event",
   "etag": "\"3101503503364000\"",
   "id": "20200322_60o30d326oo30c1g60o30db164",
   "status": "confirmed",
   "htmlLink": "https://www.google.com/calendar/event?eid=MjAyMDAzMjJfNjBvMzBkMzI2b28zMGMxZzYwbzMwZGIxNjQgaWQuaW5kb25lc2lhbiNob2xpZGF5QHY",
   "created": "2019-02-21T12:22:31.000Z",
   "updated": "2019-02-21T12:22:31.682Z",
   "summary": "Isra Mi'raj Nabi Muhammad",
   "creator": {
    "email": "id.indonesian#holiday@group.v.calendar.google.com",
    "displayName": "Hari libur di Indonesia",
    "self": true
   },
   "organizer": {
    "email": "id.indonesian#holiday@group.v.calendar.google.com",
    "displayName": "Hari libur di Indonesia",
    "self": true
   },
   "start": {
    "date": "2020-03-22"
   },
   "end": {
    "date": "2020-03-23"
   },
   "transparency": "transparent",
   "visibility": "public",
   "iCalUID": "20200322_60o30d326oo30c1g60o30db164@google.com",
   "sequence": 0,
   "eventType": "default"
  },
  {
   "kind": "calendar#event",
   "etag": "\"3101503503364000\"",
   "id": "20200410_60o30d1pcoo30c1g60o30dr56g",
   "status": "confirmed",
   "htmlLink": "https://www.google.com/calendar/event?eid=MjAyMDA0MTBfNjBvMzBkMXBjb28zMGMxZzYwbzMwZHI1NmcgaWQuaW5kb25lc2lhbiNob2xpZGF5QHY",
   "created": "2019-02-21T12:22:31.000Z",
   "updated": "2019-02-21T12:22:31.682Z",
   "summary": "Wafat Isa Almasih",
   "creator": {
    "email": "id.indonesian#holiday@group.v.calendar.google.com",
    "displayName": "Hari libur di Indonesia",
    "self": true
   },
   "organizer": {
    "email": "id.indonesian#holiday@group.v.calendar.google.com",
    "displayName": "Hari libur di Indonesia",
    "self": true
   },
   "start": {
    "date": "2020-04-10"
   },
   "end": {
    "date": "2020-04-11"
   },
   "transparency": "transparent",
   "visibility": "public",
   "iCalUID": "20200410_60o30d1pcoo30c1g60o30dr56g@google.com",
   "sequence": 0,
   "eventType": "default"
  },
  {
   "kind": "calendar#event",
   "etag": "\"3101503503364000\"",
   "id": "20200412_60o30d3160o30c1g60o30dr56g",
   "status": "confirmed",
   "htmlLink": "https://www.google.com/calendar/event?eid=MjAyMDA0MTJfNjBvMzBkMzE2MG8zMGMxZzYwbzMwZHI1NmcgaWQuaW5kb25lc2lhbiNob2xpZGF5QHY",
   "created": "2019-02-21T12:22:31.000Z",
   "updated": "2019-02-21T12:22:31.682Z",
   "summary": "Hari Paskah",
   "creator": {
    "email": "id.indonesian#holiday@group.v.calendar.google.com",
    "displayName": "Hari libur di Indonesia",
    "self": true
   },
   "organizer": {
    "email": "id.indonesian#holiday@group.v.calendar.google.com",
    "displayName": "Hari libur di Indonesia",
    "self": true
   },
   "start": {
    "date": "2020-04-12"
   },
   "end": {
    "date": "2020-04-13"
   },
   "transparency": "transparent",
   "visibility": "public",
   "iCalUID": "20200412_60o30d3160o30c1g60o30dr56g@google.com",
   "sequence": 0,
   "eventType": "default"
  },
  {
   "kind": "calendar#event",
   "etag": "\"3101503503364000\"",
   "id": "20200501_60o30o9j74o30c1g60o30dr56g",
   "status": "confirmed",
   "htmlLink": "https://www.google.com/calendar/event?eid=MjAyMDA1MDFfNjBvMzBvOWo3NG8zMGMxZzYwbzMwZHI1NmcgaWQuaW5kb25lc2lhbiNob2xpZGF5QHY",
   "created": "2019-02-21T12:22:31.000Z",
   "updated": "2019-02-21T12:22:31.682Z",
   "summary": "Hari Buruh Internasional/Pekerja",
   "creator": {
    "email": "id.indonesian#holiday@group.v.calendar.google.com",
    "displayName": "Hari libur di Indonesia",
    "self": true
   },
   "organizer": {
    "email": "id.indonesian#holiday@group.v.calendar.google.com",
    "displayName": "Hari libur di Indonesia",
    "self": true
   },
   "start": {
    "date": "2020-05-01"
   },
   "end": {
    "date": "2020-05-02"
   },
   "transparency": "transparent",
   "visibility": "public",
   "iCalUID": "20200501_60o30o9j74o30c1g60o30dr56g@google.com",
   "sequence": 0,
   "eventType": "default"
  },
  {
   "kind": "calendar#event",
   "etag": "\"3101503503364000\"",
   "id": "20200507_60o30d31cco30c1g60o30dr56g",
   "status": "confirmed",
   "htmlLink": "https://www.google.com/calendar/event?eid=MjAyMDA1MDdfNjBvMzBkMzFjY28zMGMxZzYwbzMwZHI1NmcgaWQuaW5kb25lc2lhbiNob2xpZGF5QHY",
   "created": "2019-02-21T12:22:31.000Z",
   "updated": "2019-02-21T12:22:31.682Z",
   "summary": "Hari Raya Waisak",
   "creator": {
    "email": "id.indonesian#holiday@group.v.calendar.google.com",
    "displayName": "Hari libur di Indonesia",
    "self": true
   },
   "organizer": {
    "email": "id.indonesian#holiday@group.v.calendar.google.com",
    "displayName": "Hari libur di Indonesia",
    "self": true
   },
   "start": {
    "date": "2020-05-07"
   },
   "end": {
    "date": "2020-05-08"
   },
   "transparency": "transparent",
   "visibility": "public",
   "iCalUID": "20200507_60o30d31cco30c1g60o30dr56g@google.com",
   "sequence": 0,
   "eventType": "default"
  },
  {
   "kind": "calendar#event",
   "etag": "\"3101503503364000\"",
   "id": "20200521_60o30d31cko30c1g60o30dr56g",
   "status": "confirmed",
   "htmlLink": "https://www.google.com/calendar/event?eid=MjAyMDA1MjFfNjBvMzBkMzFja28zMGMxZzYwbzMwZHI1NmcgaWQuaW5kb25lc2lhbiNob2xpZGF5QHY",
   "created": "2019-02-21T12:22:31.000Z",
   "updated": "2019-02-21T12:22:31.682Z",
   "summary": "Kenaikan Yesus Kristus",
   "creator": {
    "email": "id.indonesian#holiday@group.v.calendar.google.com",
    "displayName": "Hari libur di Indonesia",
    "self": true
   },
   "organizer": {
    "email": "id.indonesian#holiday@group.v.calendar.google.com",
    "displayName": "Hari libur di Indonesia",
    "self": true
   },
   "start": {
    "date": "2020-05-21"
   },
   "end": {
    "date": "2020-05-22"
   },
   "transparency": "transparent",
   "visibility": "public",
   "iCalUID": "20200521_60o30d31cko30c1g60o30dr56g@google.com",
   "sequence": 0,
   "eventType": "default"
  },
  {
   "kind": "calendar#event",
   "etag": "\"3101503503364000\"",
   "id": "20200525_60o30d316ko30c1g60o30db164",
   "status": "confirmed",
   "htmlLink": "https://www.google.com/calendar/event?eid=MjAyMDA1MjVfNjBvMzBkMzE2a28zMGMxZzYwbzMwZGIxNjQgaWQuaW5kb25lc2lhbiNob2xpZGF5QHY",
   "created": "2019-02-21T12:22:31.000Z",
   "updated": "2019-02-21T12:22:31.682Z",
   "summary": "Idul Fitri (Lebaran Mudik)",
   "creator": {
    "email": "id.indonesian#holiday@group.v.calendar.google.com",
    "displayName": "Hari libur di Indonesia",
    "self": true
   },
   "organizer": {
    "email": "id.indonesian#holiday@group.v.calendar.google.com",
    "displayName": "Hari libur di Indonesia",
    "self": true
   },
   "start": {
    "date": "2020-05-25"
   },
   "end": {
    "date": "2020-05-26"
   },
   "transparency": "transparent",
   "visibility": "public",
   "iCalUID": "20200525_60o30d316ko30c1g60o30db164@google.com",
   "sequence": 0,
   "eventType": "default"
  },
  {
   "kind": "calendar#event",
   "etag": "\"3101503503364000\"",
   "id": "20200601_60o32dpn70o30c1g60o30dr56g",
   "status": "confirmed",
   "htmlLink": "https://www.google.com/calendar/event?eid=MjAyMDA2MDFfNjBvMzJkcG43MG8zMGMxZzYwbzMwZHI1NmcgaWQuaW5kb25lc2lhbiNob2xpZGF5QHY",
   "created": "2019-02-21T12:22:31.000Z",
   "updated": "2019-02-21T12:22:31.682Z",
   "summary": "Hari Lahir Pancasila",
   "creator": {
    "email": "id.indonesian#holiday@group.v.calendar.google.com",
    "displayName": "Hari libur di Indonesia",
    "self": true
   },
   "organizer": {
    "email": "id.indonesian#holiday@group.v.calendar.google.com",
    "displayName": "Hari libur di Indonesia",
    "self": true
   },
   "start": {
    "date": "2020-06-01"
   },
   "end": {
    "date": "2020-06-02"
   },
   "transparency": "transparent",
   "visibility": "public",
   "iCalUID": "20200601_60o32dpn70o30c1g60o30dr56g@google.com",
   "sequence": 0,
   "eventType": "default"
  },
  {
   "kind": "calendar#event",
   "etag": "\"3101503503364000\"",
   "id": "20200731_60o30d31c8o30c1g60o30db164",
   "status": "confirmed",
   "htmlLink": "https://www.google.com/calendar/event?eid=MjAyMDA3MzFfNjBvMzBkMzFjOG8zMGMxZzYwbzMwZGIxNjQgaWQuaW5kb25lc2lhbiNob2xpZGF5QHY",
   "created": "2019-02-21T12:22:31.000Z",
   "updated": "2019-02-21T12:22:31.682Z",
   "summary": "Idul Adha (Lebaran Haji)",
   "creator": {
    "email": "id.indonesian#holiday@group.v.calendar.google.com",
    "displayName": "Hari libur di Indonesia",
    "self": true
   },
   "organizer": {
    "email": "id.indonesian#holiday@group.v.calendar.google.com",
    "displayName": "Hari libur di Indonesia",
    "self": true
   },
   "start": {
    "date": "2020-07-31"
   },
   "end": {
    "date": "2020-08-01"
   },
   "transparency": "transparent",
   "visibility": "public",
   "iCalUID": "20200731_60o30d31c8o30c1g60o30db164@google.com",
   "sequence": 0,
   "eventType": "default"
  },
  {
   "kind": "calendar#event",
   "etag": "\"3101503503364000\"",
   "id": "20200817_60o30d326co30c1g60o30dr56g",
   "status": "confirmed",
   "htmlLink": "https://www.google.com/calendar/event?eid=MjAyMDA4MTdfNjBvMzBkMzI2Y28zMGMxZzYwbzMwZHI1NmcgaWQuaW5kb25lc2lhbiNob2xpZGF5QHY",
   "created": "2019-02-21T12:22:31.000Z",
   "updated": "2019-02-21T12:22:31.682Z",
   "summary": "Hari Proklamasi Kemerdekaan R.I.",
   "creator": {
    "email": "id.indonesian#holiday@group.v.calendar.google.com",
    "displayName": "Hari libur di Indonesia",
    "self": true
   },
   "organizer": {
    "email": "id.indonesian#holiday@group.v.calendar.google.com",
    "displayName": "Hari libur di Indonesia",
    "self": true
   },
   "start": {
    "date": "2020-08-17"
   },
   "end": {
    "date": "2020-08-18"
   },
   "transparency": "transparent",
   "visibility": "public",
   "iCalUID": "20200817_60o30d326co30c1g60o30dr56g@google.com",
   "sequence": 0,
   "eventType": "default"
  },
  {
   "kind": "calendar#event",
   "etag": "\"3101503503364000\"",
   "id": "20200820_60o30d3260o30c1g60o30db168",
   "status": "confirmed",
   "htmlLink": "https://www.google.com/calendar/event?eid=MjAyMDA4MjBfNjBvMzBkMzI2MG8zMGMxZzYwbzMwZGIxNjggaWQuaW5kb25lc2lhbiNob2xpZGF5QHY",
   "created": "2019-02-21T12:22:31.000Z",
   "updated": "2019-02-21T12:22:31.682Z",
   "summary": "Satu Muharam/Tahun Baru Hijriyah",
   "creator": {
    "email": "id.indonesian#holiday@group.v.calendar.google.com",
    "displayName": "Hari libur di Indonesia",
    "self": true
   },
   "organizer": {
    "email": "id.indonesian#holiday@group.v.calendar.google.com",
    "displayName": "Hari libur di Indonesia",
    "self": true
   },
   "start": {
    "date": "2020-08-20"
   },
   "end": {
    "date": "2020-08-21"
   },
   "transparency": "transparent",
   "visibility": "public",
   "iCalUID": "20200820_60o30d3260o30c1g60o30db168@google.com",
   "sequence": 0,
   "eventType": "default"
  },
  {
   "kind": "calendar#event",
   "etag": "\"3101503503364000\"",
   "id": "20201029_60o30d3268o30c1g60o30db168",
   "status": "confirmed",
   "htmlLink": "https://www.google.com/calendar/event?eid=MjAyMDEwMjlfNjBvMzBkMzI2OG8zMGMxZzYwbzMwZGIxNjggaWQuaW5kb25lc2lhbiNob2xpZGF5QHY",
   "created": "2019-02-21T12:22:31.000Z",
   "updated": "2019-02-21T12:22:31.682Z",
   "summary": "Maulid Nabi Muhammad",
   "creator": {
    "email": "id.indonesian#holiday@group.v.calendar.google.com",
    "displayName": "Hari libur di Indonesia",
    "self": true
   },
   "organizer": {
    "email": "id.indonesian#holiday@group.v.calendar.google.com",
    "displayName": "Hari libur di Indonesia",
    "self": true
   },
   "start": {
    "date": "2020-10-29"
   },
   "end": {
    "date": "2020-10-30"
   },
   "transparency": "transparent",
   "visibility": "public",
   "iCalUID": "20201029_60o30d3268o30c1g60o30db168@google.com",
   "sequence": 0,
   "eventType": "default"
  },
  {
   "kind": "calendar#event",
   "etag": "\"3101503503364000\"",
   "id": "20201114_60o30p1nc4o30c1g60o30dr56g",
   "status": "confirmed",
   "htmlLink": "https://www.google.com/calendar/event?eid=MjAyMDExMTRfNjBvMzBwMW5jNG8zMGMxZzYwbzMwZHI1NmcgaWQuaW5kb25lc2lhbiNob2xpZGF5QHY",
   "created": "2019-02-21T12:22:31.000Z",
   "updated": "2019-02-21T12:22:31.682Z",
   "summary": "Diwali/Deepavali",
   "creator": {
    "email": "id.indonesian#holiday@group.v.calendar.google.com",
    "displayName": "Hari libur di Indonesia",
    "self": true
   },
   "organizer": {
    "email": "id.indonesian#holiday@group.v.calendar.google.com",
    "displayName": "Hari libur di Indonesia",
    "self": true
   },
   "start": {
    "date": "2020-11-14"
   },
   "end": {
    "date": "2020-11-15"
   },
   "transparency": "transparent",
   "visibility": "public",
   "iCalUID": "20201114_60o30p1nc4o30c1g60o30dr56g@google.com",
   "sequence": 0,
   "eventType": "default"
  },
  {
   "kind": "calendar#event",
   "etag": "\"3168809539810000\"",
   "id": "20200524_60o32ob4c4o30c1g60o30db164",
   "status": "confirmed",
   "htmlLink": "https://www.google.com/calendar/event?eid=MjAyMDA1MjRfNjBvMzJvYjRjNG8zMGMxZzYwbzMwZGIxNjQgaWQuaW5kb25lc2lhbiNob2xpZGF5QHY",
   "created": "2020-03-17T00:26:09.000Z",
   "updated": "2020-03-17T00:26:09.905Z",
   "summary": "Idul Fitri (Lebaran Mudik)",
   "creator": {
    "email": "id.indonesian#holiday@group.v.calendar.google.com",
    "displayName": "Hari libur di Indonesia",
    "self": true
   },
   "organizer": {
    "email": "id.indonesian#holiday@group.v.calendar.google.com",
    "displayName": "Hari libur di Indonesia",
    "self": true
   },
   "start": {
    "date": "2020-05-24"
   },
   "end": {
    "date": "2020-05-25"
   },
   "transparency": "transparent",
   "visibility": "public",
   "iCalUID": "20200524_60o32ob4c4o30c1g60o30db164@google.com",
   "sequence": 0,
   "eventType": "default"
  },
  {
   "kind": "calendar#event",
   "etag": "\"3168809539810000\"",
   "id": "20200821_60o32ob4cko30c1g60o30dr56g",
   "status": "confirmed",
   "htmlLink": "https://www.google.com/calendar/event?eid=MjAyMDA4MjFfNjBvMzJvYjRja28zMGMxZzYwbzMwZHI1NmcgaWQuaW5kb25lc2lhbiNob2xpZGF5QHY",
   "created": "2020-03-17T00:26:09.000Z",
   "updated": "2020-03-17T00:26:09.905Z",
   "summary": "Muharram / Islamic New Year Holiday",
   "creator": {
    "email": "id.indonesian#holiday@group.v.calendar.google.com",
    "displayName": "Hari libur di Indonesia",
    "self": true
   },
   "organizer": {
    "email": "id.indonesian#holiday@group.v.calendar.google.com",
    "displayName": "Hari libur di Indonesia",
    "self": true
   },
   "start": {
    "date": "2020-08-21"
   },
   "end": {
    "date": "2020-08-22"
   },
   "transparency": "transparent",
   "visibility": "public",
   "iCalUID": "20200821_60o32ob4cko30c1g60o30dr56g@google.com",
   "sequence": 0,
   "eventType": "default"
  },
  {
   "kind": "calendar#event",
   "etag": "\"3168809539810000\"",
   "id": "20201030_60o32ob4coo30c1g60o30dr56g",
   "status": "confirmed",
   "htmlLink": "https://www.google.com/calendar/event?eid=MjAyMDEwMzBfNjBvMzJvYjRjb28zMGMxZzYwbzMwZHI1NmcgaWQuaW5kb25lc2lhbiNob2xpZGF5QHY",
   "created": "2020-03-17T00:26:09.000Z",
   "updated": "2020-03-17T00:26:09.905Z",
   "summary": "The Prophet Muhammad's Birthday Holiday",
   "creator": {
    "email": "id.indonesian#holiday@group.v.calendar.google.com",
    "displayName": "Hari libur di Indonesia",
    "self": true
   },
   "organizer": {
    "email": "id.indonesian#holiday@group.v.calendar.google.com",
    "displayName": "Hari libur di Indonesia",
    "self": true
   },
   "start": {
    "date": "2020-10-30"
   },
   "end": {
    "date": "2020-10-31"
   },
   "transparency": "transparent",
   "visibility": "public",
   "iCalUID": "20201030_60o32ob4coo30c1g60o30dr56g@google.com",
   "sequence": 0,
   "eventType": "default"
  },
  {
   "kind": "calendar#event",
   "etag": "\"3181236593606000\"",
   "id": "20201028_60o32ob6coo30c1g60o30dr56g",
   "status": "confirmed",
   "htmlLink": "https://www.google.com/calendar/event?eid=MjAyMDEwMjhfNjBvMzJvYjZjb28zMGMxZzYwbzMwZHI1NmcgaWQuaW5kb25lc2lhbiNob2xpZGF5QHY",
   "created": "2020-05-27T22:24:56.000Z",
   "updated": "2020-05-27T22:24:56.803Z",
   "summary": "Cuti Bersama",
   "creator": {
    "email": "id.indonesian#holiday@group.v.calendar.google.com",
    "displayName": "Hari libur di Indonesia",
    "self": true
   },
   "organizer": {
    "email": "id.indonesian#holiday@group.v.calendar.google.com",
    "displayName": "Hari libur di Indonesia",
    "self": true
   },
   "start": {
    "date": "2020-10-28"
   },
   "end": {
    "date": "2020-10-29"
   },
   "transparency": "transparent",
   "visibility": "public",
   "iCalUID": "20201028_60o32ob6coo30c1g60o30dr56g@google.com",
   "sequence": 0,
   "eventType": "default"
  },
  {
   "kind": "calendar#event",
   "etag": "\"3209139560822000\"",
   "id": "20200325_60o30d31c4o30c1g60o30dr56g",
   "status": "confirmed",
   "htmlLink": "https://www.google.com/calendar/event?eid=MjAyMDAzMjVfNjBvMzBkMzFjNG8zMGMxZzYwbzMwZHI1NmcgaWQuaW5kb25lc2lhbiNob2xpZGF5QHY",
   "created": "2020-11-05T09:49:40.000Z",
   "updated": "2020-11-05T09:49:40.411Z",
   "summary": "Hari Suci Nyepi (Tahun Baru Saka)",
   "creator": {
    "email": "id.indonesian#holiday@group.v.calendar.google.com",
    "displayName": "Hari libur di Indonesia",
    "self": true
   },
   "organizer": {
    "email": "id.indonesian#holiday@group.v.calendar.google.com",
    "displayName": "Hari libur di Indonesia",
    "self": true
   },
   "start": {
    "date": "2020-03-25"
   },
   "end": {
    "date": "2020-03-26"
   },
   "transparency": "transparent",
   "visibility": "public",
   "iCalUID": "20200325_60o30d31c4o30c1g60o30dr56g@google.com",
   "sequence": 0,
   "eventType": "default"
  },
  {
   "kind": "calendar#event",
   "etag": "\"3220438360862000\"",
   "id": "20201224_60o30d3168o30c1g60o30dr56g",
   "status": "confirmed",
   "htmlLink": "https://www.google.com/calendar/event?eid=MjAyMDEyMjRfNjBvMzBkMzE2OG8zMGMxZzYwbzMwZHI1NmcgaWQuaW5kb25lc2lhbiNob2xpZGF5QHY",
   "created": "2021-01-09T19:06:20.000Z",
   "updated": "2021-01-09T19:06:20.431Z",
   "summary": "Cuti Bersama (Malam Natal)",
   "creator": {
    "email": "id.indonesian#holiday@group.v.calendar.google.com",
    "displayName": "Hari libur di Indonesia",
    "self": true
   },
   "organizer": {
    "email": "id.indonesian#holiday@group.v.calendar.google.com",
    "displayName": "Hari libur di Indonesia",
    "self": true
   },
   "start": {
    "date": "2020-12-24"
   },
   "end": {
    "date": "2020-12-25"
   },
   "transparency": "transparent",
   "visibility": "public",
   "iCalUID": "20201224_60o30d3168o30c1g60o30dr56g@google.com",
   "sequence": 0,
   "eventType": "default"
  },
  {
   "kind": "calendar#event",
   "etag": "\"3220438360862000\"",
   "id": "20201225_60o30d316co30c1g60o30dr56g",
   "status": "confirmed",
   "htmlLink": "https://www.google.com/calendar/event?eid=MjAyMDEyMjVfNjBvMzBkMzE2Y28zMGMxZzYwbzMwZHI1NmcgaWQuaW5kb25lc2lhbiNob2xpZGF5QHY",
   "created": "2021-01-09T19:06:20.000Z",
   "updated": "2021-01-09T19:06:20.431Z",
   "summary": "Hari Natal",
   "creator": {
    "email": "id.indonesian#holiday@group.v.calendar.google.com",
    "displayName": "Hari libur di Indonesia",
    "self": true
   },
   "organizer": {
    "email": "id.indonesian#holiday@group.v.calendar.google.com",
    "displayName": "Hari libur di Indonesia",
    "self": true
   },
   "start": {
    "date": "2020-12-25"
   },
   "end": {
    "date": "2020-12-26"
   },
   "transparency": "transparent",
   "visibility": "public",
   "iCalUID": "20201225_60o30d316co30c1g60o30dr56g@google.com",
   "sequence": 0,
   "eventType": "default"
  },
  {
   "kind": "calendar#event",
   "etag": "\"3220438360862000\"",
   "id": "20201231_60o30d1pcco30c1g60o30dr56g",
   "status": "confirmed",
   "htmlLink": "https://www.google.com/calendar/event?eid=MjAyMDEyMzFfNjBvMzBkMXBjY28zMGMxZzYwbzMwZHI1NmcgaWQuaW5kb25lc2lhbiNob2xpZGF5QHY",
   "created": "2021-01-09T19:06:20.000Z",
   "updated": "2021-01-09T19:06:20.431Z",
   "summary": "Malam Tahun Baru",
   "creator": {
    "email": "id.indonesian#holiday@group.v.calendar.google.com",
    "displayName": "Hari libur di Indonesia",
    "self": true
   },
   "organizer": {
    "email": "id.indonesian#holiday@group.v.calendar.google.com",
    "displayName": "Hari libur di Indonesia",
    "self": true
   },
   "start": {
    "date": "2020-12-31"
   },
   "end": {
    "date": "2021-01-01"
   },
   "transparency": "transparent",
   "visibility": "public",
   "iCalUID": "20201231_60o30d1pcco30c1g60o30dr56g@google.com",
   "sequence": 0,
   "eventType": "default"
  },
  {
   "kind": "calendar#event",
   "etag": "\"3220438360862000\"",
   "id": "20201231_60o32ohl6go36c1g60o30dr56g",
   "status": "confirmed",
   "htmlLink": "https://www.google.com/calendar/event?eid=MjAyMDEyMzFfNjBvMzJvaGw2Z28zNmMxZzYwbzMwZHI1NmcgaWQuaW5kb25lc2lhbiNob2xpZGF5QHY",
   "created": "2021-01-09T19:06:20.000Z",
   "updated": "2021-01-09T19:06:20.431Z",
   "summary": "Cuti Bersama",
   "creator": {
    "email": "id.indonesian#holiday@group.v.calendar.google.com",
    "displayName": "Hari libur di Indonesia",
    "self": true
   },
   "organizer": {
    "email": "id.indonesian#holiday@group.v.calendar.google.com",
    "displayName": "Hari libur di Indonesia",
    "self": true
   },
   "start": {
    "date": "2020-12-31"
   },
   "end": {
    "date": "2021-01-01"
   },
   "transparency": "transparent",
   "visibility": "public",
   "iCalUID": "20201231_60o32ohl6go36c1g60o30dr56g@google.com",
   "sequence": 0,
   "eventType": "default"
  },
  {
   "kind": "calendar#event",
   "etag": "\"3220438360862000\"",
   "id": "20210101_60o30d1pcgo30c1g60o30dr56k",
   "status": "confirmed",
   "htmlLink": "https://www.google.com/calendar/event?eid=MjAyMTAxMDFfNjBvMzBkMXBjZ28zMGMxZzYwbzMwZHI1NmsgaWQuaW5kb25lc2lhbiNob2xpZGF5QHY",
   "created": "2021-01-09T19:06:20.000Z",
   "updated": "2021-01-09T19:06:20.431Z",
   "summary": "Hari Tahun Baru",
   "creator": {
    "email": "id.indonesian#holiday@group.v.calendar.google.com",
    "displayName": "Hari libur di Indonesia",
    "self": true
   },
   "organizer": {
    "email": "id.indonesian#holiday@group.v.calendar.google.com",
    "displayName": "Hari libur di Indonesia",
    "self": true
   },
   "start": {
    "date": "2021-01-01"
   },
   "end": {
    "date": "2021-01-02"
   },
   "transparency": "transparent",
   "visibility": "public",
   "iCalUID": "20210101_60o30d1pcgo30c1g60o30dr56k@google.com",
   "sequence": 0,
   "eventType": "default"
  },
  {
   "kind": "calendar#event",
   "etag": "\"3220438360862000\"",
   "id": "20210212_60o30d326go30c1g60o32chmck",
   "status": "confirmed",
   "htmlLink": "https://www.google.com/calendar/event?eid=MjAyMTAyMTJfNjBvMzBkMzI2Z28zMGMxZzYwbzMyY2htY2sgaWQuaW5kb25lc2lhbiNob2xpZGF5QHY",
   "created": "2021-01-09T19:06:20.000Z",
   "updated": "2021-01-09T19:06:20.431Z",
   "summary": "Tahun Baru Imlek",
   "creator": {
    "email": "id.indonesian#holiday@group.v.calendar.google.com",
    "displayName": "Hari libur di Indonesia",
    "self": true
   },
   "organizer": {
    "email": "id.indonesian#holiday@group.v.calendar.google.com",
    "displayName": "Hari libur di Indonesia",
    "self": true
   },
   "start": {
    "date": "2021-02-12"
   },
   "end": {
    "date": "2021-02-13"
   },
   "transparency": "transparent",
   "visibility": "public",
   "iCalUID": "20210212_60o30d326go30c1g60o32chmck@google.com",
   "sequence": 0,
   "eventType": "default"
  },
  {
   "kind": "calendar#event",
   "etag": "\"3220438360862000\"",
   "id": "20210311_60o30d326oo30c1g60o30db168",
   "status": "confirmed",
   "htmlLink": "https://www.google.com/calendar/event?eid=MjAyMTAzMTFfNjBvMzBkMzI2b28zMGMxZzYwbzMwZGIxNjggaWQuaW5kb25lc2lhbiNob2xpZGF5QHY",
   "created": "2021-01-09T19:06:20.000Z",
   "updated": "2021-01-09T19:06:20.431Z",
   "summary": "Isra Mi'raj Nabi Muhammad",
   "creator": {
    "email": "id.indonesian#holiday@group.v.calendar.google.com",
    "displayName": "Hari libur di Indonesia",
    "self": true
   },
   "organizer": {
    "email": "id.indonesian#holiday@group.v.calendar.google.com",
    "displayName": "Hari libur di Indonesia",
    "self": true
   },
   "start": {
    "date": "2021-03-11"
   },
   "end": {
    "date": "2021-03-12"
   },
   "transparency": "transparent",
   "visibility": "public",
   "iCalUID": "20210311_60o30d326oo30c1g60o30db168@google.com",
   "sequence": 0,
   "eventType": "default"
  },
  {
   "kind": "calendar#event",
   "etag": "\"3220438360862000\"",
   "id": "20210312_60o32ohl6go30c1g60o30dr56k",
   "status": "confirmed",
   "htmlLink": "https://www.google.com/calendar/event?eid=MjAyMTAzMTJfNjBvMzJvaGw2Z28zMGMxZzYwbzMwZHI1NmsgaWQuaW5kb25lc2lhbiNob2xpZGF5QHY",
   "created": "2021-01-09T19:06:20.000Z",
   "updated": "2021-01-09T19:06:20.431Z",
   "summary": "Cuti Bersama",
   "creator": {
    "email": "id.indonesian#holiday@group.v.calendar.google.com",
    "displayName": "Hari libur di Indonesia",
    "self": true
   },
   "organizer": {
    "email": "id.indonesian#holiday@group.v.calendar.google.com",
    "displayName": "Hari libur di Indonesia",
    "self": true
   },
   "start": {
    "date": "2021-03-12"
   },
   "end": {
    "date": "2021-03-13"
   },
   "transparency": "transparent",
   "visibility": "public",
   "iCalUID": "20210312_60o32ohl6go30c1g60o30dr56k@google.com",
   "sequence": 0,
   "eventType": "default"
  },
  {
   "kind": "calendar#event",
   "etag": "\"3220438360862000\"",
   "id": "20210314_60o30d31c4o30c1g60o30dr56k",
   "status": "confirmed",
   "htmlLink": "https://www.google.com/calendar/event?eid=MjAyMTAzMTRfNjBvMzBkMzFjNG8zMGMxZzYwbzMwZHI1NmsgaWQuaW5kb25lc2lhbiNob2xpZGF5QHY",
   "created": "2021-01-09T19:06:20.000Z",
   "updated": "2021-01-09T19:06:20.431Z",
   "summary": "Hari Suci Nyepi (Tahun Baru Saka)",
   "creator": {
    "email": "id.indonesian#holiday@group.v.calendar.google.com",
    "displayName": "Hari libur di Indonesia",
    "self": true
   },
   "organizer": {
    "email": "id.indonesian#holiday@group.v.calendar.google.com",
    "displayName": "Hari libur di Indonesia",
    "self": true
   },
   "start": {
    "date": "2021-03-14"
   },
   "end": {
    "date": "2021-03-15"
   },
   "transparency": "transparent",
   "visibility": "public",
   "iCalUID": "20210314_60o30d31c4o30c1g60o30dr56k@google.com",
   "sequence": 0,
   "eventType": "default"
  },
  {
   "kind": "calendar#event",
   "etag": "\"3220438360862000\"",
   "id": "20210402_60o30d1pcoo30c1g60o30dr56k",
   "status": "confirmed",
   "htmlLink": "https://www.google.com/calendar/event?eid=MjAyMTA0MDJfNjBvMzBkMXBjb28zMGMxZzYwbzMwZHI1NmsgaWQuaW5kb25lc2lhbiNob2xpZGF5QHY",
   "created": "2021-01-09T19:06:20.000Z",
   "updated": "2021-01-09T19:06:20.431Z",
   "summary": "Wafat Isa Almasih",
   "creator": {
    "email": "id.indonesian#holiday@group.v.calendar.google.com",
    "displayName": "Hari libur di Indonesia",
    "self": true
   },
   "organizer": {
    "email": "id.indonesian#holiday@group.v.calendar.google.com",
    "displayName": "Hari libur di Indonesia",
    "self": true
   },
   "start": {
    "date": "2021-04-02"
   },
   "end": {
    "date": "2021-04-03"
   },
   "transparency": "transparent",
   "visibility": "public",
   "iCalUID": "20210402_60o30d1pcoo30c1g60o30dr56k@google.com",
   "sequence": 0,
   "eventType": "default"
  },
  {
   "kind": "calendar#event",
   "etag": "\"3220438360862000\"",
   "id": "20210404_60o30d3160o30c1g60o30dr56k",
   "status": "confirmed",
   "htmlLink": "https://www.google.com/calendar/event?eid=MjAyMTA0MDRfNjBvMzBkMzE2MG8zMGMxZzYwbzMwZHI1NmsgaWQuaW5kb25lc2lhbiNob2xpZGF5QHY",
   "created": "2021-01-09T19:06:20.000Z",
   "updated": "2021-01-09T19:06:20.431Z",
   "summary": "Hari Paskah",
   "creator": {
    "email": "id.indonesian#holiday@group.v.calendar.google.com",
    "displayName": "Hari libur di Indonesia",
    "self": true
   },
   "organizer": {
    "email": "id.indonesian#holiday@group.v.calendar.google.com",
    "displayName": "Hari libur di Indonesia",
    "self": true
   },
   "start": {
    "date": "2021-04-04"
   },
   "end": {
    "date": "2021-04-05"
   },
   "transparency": "transparent",
   "visibility": "public",
   "iCalUID": "20210404_60o30d3160o30c1g60o30dr56k@google.com",
   "sequence": 0,
   "eventType": "default"
  },
  {
   "kind": "calendar#event",
   "etag": "\"3220438360862000\"",
   "id": "20210501_60o30o9j74o30c1g60o30dr56k",
   "status": "confirmed",
   "htmlLink": "https://www.google.com/calendar/event?eid=MjAyMTA1MDFfNjBvMzBvOWo3NG8zMGMxZzYwbzMwZHI1NmsgaWQuaW5kb25lc2lhbiNob2xpZGF5QHY",
   "created": "2021-01-09T19:06:20.000Z",
   "updated": "2021-01-09T19:06:20.431Z",
   "summary": "Hari Buruh Internasional/Pekerja",
   "creator": {
    "email": "id.indonesian#holiday@group.v.calendar.google.com",
    "displayName": "Hari libur di Indonesia",
    "self": true
   },
   "organizer": {
    "email": "id.indonesian#holiday@group.v.calendar.google.com",
    "displayName": "Hari libur di Indonesia",
    "self": true
   },
   "start": {
    "date": "2021-05-01"
   },
   "end": {
    "date": "2021-05-02"
   },
   "transparency": "transparent",
   "visibility": "public",
   "iCalUID": "20210501_60o30o9j74o30c1g60o30dr56k@google.com",
   "sequence": 0,
   "eventType": "default"
  },
  {
   "kind": "calendar#event",
   "etag": "\"3220438360862000\"",
   "id": "20210512_60o30d316oo30c1g60o30dr56k",
   "status": "confirmed",
   "htmlLink": "https://www.google.com/calendar/event?eid=MjAyMTA1MTJfNjBvMzBkMzE2b28zMGMxZzYwbzMwZHI1NmsgaWQuaW5kb25lc2lhbiNob2xpZGF5QHY",
   "created": "2021-01-09T19:06:20.000Z",
   "updated": "2021-01-09T19:06:20.431Z",
   "summary": "Cuti Bersama",
   "creator": {
    "email": "id.indonesian#holiday@group.v.calendar.google.com",
    "displayName": "Hari libur di Indonesia",
    "self": true
   },
   "organizer": {
    "email": "id.indonesian#holiday@group.v.calendar.google.com",
    "displayName": "Hari libur di Indonesia",
    "self": true
   },
   "start": {
    "date": "2021-05-12"
   },
   "end": {
    "date": "2021-05-13"
   },
   "transparency": "transparent",
   "visibility": "public",
   "iCalUID": "20210512_60o30d316oo30c1g60o30dr56k@google.com",
   "sequence": 0,
   "eventType": "default"
  },
  {
   "kind": "calendar#event",
   "etag": "\"3220438360862000\"",
   "id": "20210513_60o30d31cko30c1g60o30dr56k",
   "status": "confirmed",
   "htmlLink": "https://www.google.com/calendar/event?eid=MjAyMTA1MTNfNjBvMzBkMzFja28zMGMxZzYwbzMwZHI1NmsgaWQuaW5kb25lc2lhbiNob2xpZGF5QHY",
   "created": "2021-01-09T19:06:20.000Z",
   "updated": "2021-01-09T19:06:20.431Z",
   "summary": "Kenaikan Yesus Kristus",
   "creator": {
    "email": "id.indonesian#holiday@group.v.calendar.google.com",
    "displayName": "Hari libur di Indonesia",
    "self": true
   },
   "organizer": {
    "email": "id.indonesian#holiday@group.v.calendar.google.com",
    "displayName": "Hari libur di Indonesia",
    "self": true
   },
   "start": {
    "date": "2021-05-13"
   },
   "end": {
    "date": "2021-05-14"
   },
   "transparency": "transparent",
   "visibility": "public",
   "iCalUID": "20210513_60o30d31cko30c1g60o30dr56k@google.com",
   "sequence": 0,
   "eventType": "default"
  },
  {
   "kind": "calendar#event",
   "etag": "\"3220438360862000\"",
   "id": "20210513_60o32ob4c4o30c1g60o30db168",
   "status": "confirmed",
   "htmlLink": "https://www.google.com/calendar/event?eid=MjAyMTA1MTNfNjBvMzJvYjRjNG8zMGMxZzYwbzMwZGIxNjggaWQuaW5kb25lc2lhbiNob2xpZGF5QHY",
   "created": "2021-01-09T19:06:20.000Z",
   "updated": "2021-01-09T19:06:20.431Z",
   "summary": "Idul Fitri (Lebaran Mudik)",
   "creator": {
    "email": "id.indonesian#holiday@group.v.calendar.google.com",
    "displayName": "Hari libur di Indonesia",
    "self": true
   },
   "organizer": {
    "email": "id.indonesian#holiday@group.v.calendar.google.com",
    "displayName": "Hari libur di Indonesia",
    "self": true
   },
   "start": {
    "date": "2021-05-13"
   },
   "end": {
    "date": "2021-05-14"
   },
   "transparency": "transparent",
   "visibility": "public",
   "iCalUID": "20210513_60o32ob4c4o30c1g60o30db168@google.com",
   "sequence": 0,
   "eventType": "default"
  },
  {
   "kind": "calendar#event",
   "etag": "\"3220438360862000\"",
   "id": "20210514_60o30d316ko30c1g60o30db168",
   "status": "confirmed",
   "htmlLink": "https://www.google.com/calendar/event?eid=MjAyMTA1MTRfNjBvMzBkMzE2a28zMGMxZzYwbzMwZGIxNjggaWQuaW5kb25lc2lhbiNob2xpZGF5QHY",
   "created": "2021-01-09T19:06:20.000Z",
   "updated": "2021-01-09T19:06:20.431Z",
   "summary": "Idul Fitri (Lebaran Mudik)",
   "creator": {
    "email": "id.indonesian#holiday@group.v.calendar.google.com",
    "displayName": "Hari libur di Indonesia",
    "self": true
   },
   "organizer": {
    "email": "id.indonesian#holiday@group.v.calendar.google.com",
    "displayName": "Hari libur di Indonesia",
    "self": true
   },
   "start": {
    "date": "2021-05-14"
   },
   "end": {
    "date": "2021-05-15"
   },
   "transparency": "transparent",
   "visibility": "public",
   "iCalUID": "20210514_60o30d316ko30c1g60o30db168@google.com",
   "sequence": 0,
   "eventType": "default"
  },
  {
   "kind": "calendar#event",
   "etag": "\"3220438360862000\"",
   "id": "20210517_60o30d3170o30c1g60o30dr56k",
   "status": "confirmed",
   "htmlLink": "https://www.google.com/calendar/event?eid=MjAyMTA1MTdfNjBvMzBkMzE3MG8zMGMxZzYwbzMwZHI1NmsgaWQuaW5kb25lc2lhbiNob2xpZGF5QHY",
   "created": "2021-01-09T19:06:20.000Z",
   "updated": "2021-01-09T19:06:20.431Z",
   "summary": "Cuti Bersama",
   "creator": {
    "email": "id.indonesian#holiday@group.v.calendar.google.com",
    "displayName": "Hari libur di Indonesia",
    "self": true
   },
   "organizer": {
    "email": "id.indonesian#holiday@group.v.calendar.google.com",
    "displayName": "Hari libur di Indonesia",
    "self": true
   },
   "start": {
    "date": "2021-05-17"
   },
   "end": {
    "date": "2021-05-18"
   },
   "transparency": "transparent",
   "visibility": "public",
   "iCalUID": "20210517_60o30d3170o30c1g60o30dr56k@google.com",
   "sequence": 0,
   "eventType": "default"
  },
  {
   "kind": "calendar#event",
   "etag": "\"3220438360862000\"",
   "id": "20210518_60o30d3174o30c1g60o30dr56k",
   "status": "confirmed",
   "htmlLink": "https://www.google.com/calendar/event?eid=MjAyMTA1MThfNjBvMzBkMzE3NG8zMGMxZzYwbzMwZHI1NmsgaWQuaW5kb25lc2lhbiNob2xpZGF5QHY",
   "created": "2021-01-09T19:06:20.000Z",
   "updated": "2021-01-09T19:06:20.431Z",
   "summary": "Cuti Bersama",
   "creator": {
    "email": "id.indonesian#holiday@group.v.calendar.google.com",
    "displayName": "Hari libur di Indonesia",
    "self": true
   },
   "organizer": {
    "email": "id.indonesian#holiday@group.v.calendar.google.com",
    "displayName": "Hari libur di Indonesia",
    "self": true
   },
   "start": {
    "date": "2021-05-18"
   },
   "end": {
    "date": "2021-05-19"
   },
   "transparency": "transparent",
   "visibility": "public",
   "iCalUID": "20210518_60o30d3174o30c1g60o30dr56k@google.com",
   "sequence": 0,
   "eventType": "default"
  },
  {
   "kind": "calendar#event",
   "etag": "\"3220438360862000\"",
   "id": "20210526_60o30d31cco30c1g60o30dr56k",
   "status": "confirmed",
   "htmlLink": "https://www.google.com/calendar/event?eid=MjAyMTA1MjZfNjBvMzBkMzFjY28zMGMxZzYwbzMwZHI1NmsgaWQuaW5kb25lc2lhbiNob2xpZGF5QHY",
   "created": "2021-01-09T19:06:20.000Z",
   "updated": "2021-01-09T19:06:20.431Z",
   "summary": "Hari Raya Waisak",
   "creator": {
    "email": "id.indonesian#holiday@group.v.calendar.google.com",
    "displayName": "Hari libur di Indonesia",
    "self": true
   },
   "organizer": {
    "email": "id.indonesian#holiday@group.v.calendar.google.com",
    "displayName": "Hari libur di Indonesia",
    "self": true
   },
   "start": {
    "date": "2021-05-26"
   },
   "end": {
    "date": "2021-05-27"
   },
   "transparency": "transparent",
   "visibility": "public",
   "iCalUID": "20210526_60o30d31cco30c1g60o30dr56k@google.com",
   "sequence": 0,
   "eventType": "default"
  },
  {
   "kind": "calendar#event",
   "etag": "\"3220438360862000\"",
   "id": "20210601_60o32dpn70o30c1g60o30dr56k",
   "status": "confirmed",
   "htmlLink": "https://www.google.com/calendar/event?eid=MjAyMTA2MDFfNjBvMzJkcG43MG8zMGMxZzYwbzMwZHI1NmsgaWQuaW5kb25lc2lhbiNob2xpZGF5QHY",
   "created": "2021-01-09T19:06:20.000Z",
   "updated": "2021-01-09T19:06:20.431Z",
   "summary": "Hari Lahir Pancasila",
   "creator": {
    "email": "id.indonesian#holiday@group.v.calendar.google.com",
    "displayName": "Hari libur di Indonesia",
    "self": true
   },
   "organizer": {
    "email": "id.indonesian#holiday@group.v.calendar.google.com",
    "displayName": "Hari libur di Indonesia",
    "self": true
   },
   "start": {
    "date": "2021-06-01"
   },
   "end": {
    "date": "2021-06-02"
   },
   "transparency": "transparent",
   "visibility": "public",
   "iCalUID": "20210601_60o32dpn70o30c1g60o30dr56k@google.com",
   "sequence": 0,
   "eventType": "default"
  },
  {
   "kind": "calendar#event",
   "etag": "\"3220438360862000\"",
   "id": "20210720_60o30d31c8o30c1g60o30db168",
   "status": "confirmed",
   "htmlLink": "https://www.google.com/calendar/event?eid=MjAyMTA3MjBfNjBvMzBkMzFjOG8zMGMxZzYwbzMwZGIxNjggaWQuaW5kb25lc2lhbiNob2xpZGF5QHY",
   "created": "2021-01-09T19:06:20.000Z",
   "updated": "2021-01-09T19:06:20.431Z",
   "summary": "Idul Adha (Lebaran Haji)",
   "creator": {
    "email": "id.indonesian#holiday@group.v.calendar.google.com",
    "displayName": "Hari libur di Indonesia",
    "self": true
   },
   "organizer": {
    "email": "id.indonesian#holiday@group.v.calendar.google.com",
    "displayName": "Hari libur di Indonesia",
    "self": true
   },
   "start": {
    "date": "2021-07-20"
   },
   "end": {
    "date": "2021-07-21"
   },
   "transparency": "transparent",
   "visibility": "public",
   "iCalUID": "20210720_60o30d31c8o30c1g60o30db168@google.com",
   "sequence": 0,
   "eventType": "default"
  },
  {
   "kind": "calendar#event",
   "etag": "\"3220438360862000\"",
   "id": "20210810_60o30d3260o30c1g60o30db16c",
   "status": "confirmed",
   "htmlLink": "https://www.google.com/calendar/event?eid=MjAyMTA4MTBfNjBvMzBkMzI2MG8zMGMxZzYwbzMwZGIxNmMgaWQuaW5kb25lc2lhbiNob2xpZGF5QHY",
   "created": "2021-01-09T19:06:20.000Z",
   "updated": "2021-01-09T19:06:20.431Z",
   "summary": "Satu Muharam/Tahun Baru Hijriyah",
   "creator": {
    "email": "id.indonesian#holiday@group.v.calendar.google.com",
    "displayName": "Hari libur di Indonesia",
    "self": true
   },
   "organizer": {
    "email": "id.indonesian#holiday@group.v.calendar.google.com",
    "displayName": "Hari libur di Indonesia",
    "self": true
   },
   "start": {
    "date": "2021-08-10"
   },
   "end": {
    "date": "2021-08-11"
   },
   "transparency": "transparent",
   "visibility": "public",
   "iCalUID": "20210810_60o30d3260o30c1g60o30db16c@google.com",
   "sequence": 0,
   "eventType": "default"
  },
  {
   "kind": "calendar#event",
   "etag": "\"3220438360862000\"",
   "id": "20210817_60o30d326co30c1g60o30dr56k",
   "status": "confirmed",
   "htmlLink": "https://www.google.com/calendar/event?eid=MjAyMTA4MTdfNjBvMzBkMzI2Y28zMGMxZzYwbzMwZHI1NmsgaWQuaW5kb25lc2lhbiNob2xpZGF5QHY",
   "created": "2021-01-09T19:06:20.000Z",
   "updated": "2021-01-09T19:06:20.431Z",
   "summary": "Hari Proklamasi Kemerdekaan R.I.",
   "creator": {
    "email": "id.indonesian#holiday@group.v.calendar.google.com",
    "displayName": "Hari libur di Indonesia",
    "self": true
   },
   "organizer": {
    "email": "id.indonesian#holiday@group.v.calendar.google.com",
    "displayName": "Hari libur di Indonesia",
    "self": true
   },
   "start": {
    "date": "2021-08-17"
   },
   "end": {
    "date": "2021-08-18"
   },
   "transparency": "transparent",
   "visibility": "public",
   "iCalUID": "20210817_60o30d326co30c1g60o30dr56k@google.com",
   "sequence": 0,
   "eventType": "default"
  },
  {
   "kind": "calendar#event",
   "etag": "\"3220438360862000\"",
   "id": "20211019_60o30d3268o30c1g60o30db16c",
   "status": "confirmed",
   "htmlLink": "https://www.google.com/calendar/event?eid=MjAyMTEwMTlfNjBvMzBkMzI2OG8zMGMxZzYwbzMwZGIxNmMgaWQuaW5kb25lc2lhbiNob2xpZGF5QHY",
   "created": "2021-01-09T19:06:20.000Z",
   "updated": "2021-01-09T19:06:20.431Z",
   "summary": "Maulid Nabi Muhammad",
   "creator": {
    "email": "id.indonesian#holiday@group.v.calendar.google.com",
    "displayName": "Hari libur di Indonesia",
    "self": true
   },
   "organizer": {
    "email": "id.indonesian#holiday@group.v.calendar.google.com",
    "displayName": "Hari libur di Indonesia",
    "self": true
   },
   "start": {
    "date": "2021-10-19"
   },
   "end": {
    "date": "2021-10-20"
   },
   "transparency": "transparent",
   "visibility": "public",
   "iCalUID": "20211019_60o30d3268o30c1g60o30db16c@google.com",
   "sequence": 0,
   "eventType": "default"
  },
  {
   "kind": "calendar#event",
   "etag": "\"3220438360862000\"",
   "id": "20211104_60o30p1nc4o30c1g60o30dr56k",
   "status": "confirmed",
   "htmlLink": "https://www.google.com/calendar/event?eid=MjAyMTExMDRfNjBvMzBwMW5jNG8zMGMxZzYwbzMwZHI1NmsgaWQuaW5kb25lc2lhbiNob2xpZGF5QHY",
   "created": "2021-01-09T19:06:20.000Z",
   "updated": "2021-01-09T19:06:20.431Z",
   "summary": "Diwali/Deepavali",
   "creator": {
    "email": "id.indonesian#holiday@group.v.calendar.google.com",
    "displayName": "Hari libur di Indonesia",
    "self": true
   },
   "organizer": {
    "email": "id.indonesian#holiday@group.v.calendar.google.com",
    "displayName": "Hari libur di Indonesia",
    "self": true
   },
   "start": {
    "date": "2021-11-04"
   },
   "end": {
    "date": "2021-11-05"
   },
   "transparency": "transparent",
   "visibility": "public",
   "iCalUID": "20211104_60o30p1nc4o30c1g60o30dr56k@google.com",
   "sequence": 0,
   "eventType": "default"
  },
  {
   "kind": "calendar#event",
   "etag": "\"3220438360862000\"",
   "id": "20211224_60o30d3168o30c1g60o30dr56k",
   "status": "confirmed",
   "htmlLink": "https://www.google.com/calendar/event?eid=MjAyMTEyMjRfNjBvMzBkMzE2OG8zMGMxZzYwbzMwZHI1NmsgaWQuaW5kb25lc2lhbiNob2xpZGF5QHY",
   "created": "2021-01-09T19:06:20.000Z",
   "updated": "2021-01-09T19:06:20.431Z",
   "summary": "Cuti Bersama (Malam Natal)",
   "creator": {
    "email": "id.indonesian#holiday@group.v.calendar.google.com",
    "displayName": "Hari libur di Indonesia",
    "self": true
   },
   "organizer": {
    "email": "id.indonesian#holiday@group.v.calendar.google.com",
    "displayName": "Hari libur di Indonesia",
    "self": true
   },
   "start": {
    "date": "2021-12-24"
   },
   "end": {
    "date": "2021-12-25"
   },
   "transparency": "transparent",
   "visibility": "public",
   "iCalUID": "20211224_60o30d3168o30c1g60o30dr56k@google.com",
   "sequence": 0,
   "eventType": "default"
  },
  {
   "kind": "calendar#event",
   "etag": "\"3220438360862000\"",
   "id": "20211225_60o30d316co30c1g60o30dr56k",
   "status": "confirmed",
   "htmlLink": "https://www.google.com/calendar/event?eid=MjAyMTEyMjVfNjBvMzBkMzE2Y28zMGMxZzYwbzMwZHI1NmsgaWQuaW5kb25lc2lhbiNob2xpZGF5QHY",
   "created": "2021-01-09T19:06:20.000Z",
   "updated": "2021-01-09T19:06:20.431Z",
   "summary": "Hari Natal",
   "creator": {
    "email": "id.indonesian#holiday@group.v.calendar.google.com",
    "displayName": "Hari libur di Indonesia",
    "self": true
   },
   "organizer": {
    "email": "id.indonesian#holiday@group.v.calendar.google.com",
    "displayName": "Hari libur di Indonesia",
    "self": true
   },
   "start": {
    "date": "2021-12-25"
   },
   "end": {
    "date": "2021-12-26"
   },
   "transparency": "transparent",
   "visibility": "public",
   "iCalUID": "20211225_60o30d316co30c1g60o30dr56k@google.com",
   "sequence": 0,
   "eventType": "default"
  },
  {
   "kind": "calendar#event",
   "etag": "\"3220438360862000\"",
   "id": "20211226_60o30o9jc4o30c1g60o30dr56k",
   "status": "confirmed",
   "htmlLink": "https://www.google.com/calendar/event?eid=MjAyMTEyMjZfNjBvMzBvOWpjNG8zMGMxZzYwbzMwZHI1NmsgaWQuaW5kb25lc2lhbiNob2xpZGF5QHY",
   "created": "2021-01-09T19:06:20.000Z",
   "updated": "2021-01-09T19:06:20.431Z",
   "summary": "Jumat untuk Hari Raya Natal",
   "creator": {
    "email": "id.indonesian#holiday@group.v.calendar.google.com",
    "displayName": "Hari libur di Indonesia",
    "self": true
   },
   "organizer": {
    "email": "id.indonesian#holiday@group.v.calendar.google.com",
    "displayName": "Hari libur di Indonesia",
    "self": true
   },
   "start": {
    "date": "2021-12-26"
   },
   "end": {
    "date": "2021-12-27"
   },
   "transparency": "transparent",
   "visibility": "public",
   "iCalUID": "20211226_60o30o9jc4o30c1g60o30dr56k@google.com",
   "sequence": 0,
   "eventType": "default"
  },
  {
   "kind": "calendar#event",
   "etag": "\"3220438360862000\"",
   "id": "20211231_60o30d1pcco30c1g60o30dr56k",
   "status": "confirmed",
   "htmlLink": "https://www.google.com/calendar/event?eid=MjAyMTEyMzFfNjBvMzBkMXBjY28zMGMxZzYwbzMwZHI1NmsgaWQuaW5kb25lc2lhbiNob2xpZGF5QHY",
   "created": "2021-01-09T19:06:20.000Z",
   "updated": "2021-01-09T19:06:20.431Z",
   "summary": "Malam Tahun Baru",
   "creator": {
    "email": "id.indonesian#holiday@group.v.calendar.google.com",
    "displayName": "Hari libur di Indonesia",
    "self": true
   },
   "organizer": {
    "email": "id.indonesian#holiday@group.v.calendar.google.com",
    "displayName": "Hari libur di Indonesia",
    "self": true
   },
   "start": {
    "date": "2021-12-31"
   },
   "end": {
    "date": "2022-01-01"
   },
   "transparency": "transparent",
   "visibility": "public",
   "iCalUID": "20211231_60o30d1pcco30c1g60o30dr56k@google.com",
   "sequence": 0,
   "eventType": "default"
  },
  {
   "kind": "calendar#event",
   "etag": "\"3220438360862000\"",
   "id": "20220101_60o30d1pcgo30c1g60o30dr56o",
   "status": "confirmed",
   "htmlLink": "https://www.google.com/calendar/event?eid=MjAyMjAxMDFfNjBvMzBkMXBjZ28zMGMxZzYwbzMwZHI1Nm8gaWQuaW5kb25lc2lhbiNob2xpZGF5QHY",
   "created": "2021-01-09T19:06:20.000Z",
   "updated": "2021-01-09T19:06:20.431Z",
   "summary": "Hari Tahun Baru",
   "creator": {
    "email": "id.indonesian#holiday@group.v.calendar.google.com",
    "displayName": "Hari libur di Indonesia",
    "self": true
   },
   "organizer": {
    "email": "id.indonesian#holiday@group.v.calendar.google.com",
    "displayName": "Hari libur di Indonesia",
    "self": true
   },
   "start": {
    "date": "2022-01-01"
   },
   "end": {
    "date": "2022-01-02"
   },
   "transparency": "transparent",
   "visibility": "public",
   "iCalUID": "20220101_60o30d1pcgo30c1g60o30dr56o@google.com",
   "sequence": 0,
   "eventType": "default"
  },
  {
   "kind": "calendar#event",
   "etag": "\"3220438360862000\"",
   "id": "20220201_60o30d326go30c1g60o32chmco",
   "status": "confirmed",
   "htmlLink": "https://www.google.com/calendar/event?eid=MjAyMjAyMDFfNjBvMzBkMzI2Z28zMGMxZzYwbzMyY2htY28gaWQuaW5kb25lc2lhbiNob2xpZGF5QHY",
   "created": "2021-01-09T19:06:20.000Z",
   "updated": "2021-01-09T19:06:20.431Z",
   "summary": "Tahun Baru Imlek",
   "creator": {
    "email": "id.indonesian#holiday@group.v.calendar.google.com",
    "displayName": "Hari libur di Indonesia",
    "self": true
   },
   "organizer": {
    "email": "id.indonesian#holiday@group.v.calendar.google.com",
    "displayName": "Hari libur di Indonesia",
    "self": true
   },
   "start": {
    "date": "2022-02-01"
   },
   "end": {
    "date": "2022-02-02"
   },
   "transparency": "transparent",
   "visibility": "public",
   "iCalUID": "20220201_60o30d326go30c1g60o32chmco@google.com",
   "sequence": 0,
   "eventType": "default"
  },
  {
   "kind": "calendar#event",
   "etag": "\"3220438360862000\"",
   "id": "20220301_60o30d326oo30c1g60o30db16c",
   "status": "confirmed",
   "htmlLink": "https://www.google.com/calendar/event?eid=MjAyMjAzMDFfNjBvMzBkMzI2b28zMGMxZzYwbzMwZGIxNmMgaWQuaW5kb25lc2lhbiNob2xpZGF5QHY",
   "created": "2021-01-09T19:06:20.000Z",
   "updated": "2021-01-09T19:06:20.431Z",
   "summary": "Isra Mi'raj Nabi Muhammad",
   "creator": {
    "email": "id.indonesian#holiday@group.v.calendar.google.com",
    "displayName": "Hari libur di Indonesia",
    "self": true
   },
   "organizer": {
    "email": "id.indonesian#holiday@group.v.calendar.google.com",
    "displayName": "Hari libur di Indonesia",
    "self": true
   },
   "start": {
    "date": "2022-03-01"
   },
   "end": {
    "date": "2022-03-02"
   },
   "transparency": "transparent",
   "visibility": "public",
   "iCalUID": "20220301_60o30d326oo30c1g60o30db16c@google.com",
   "sequence": 0,
   "eventType": "default"
  },
  {
   "kind": "calendar#event",
   "etag": "\"3220438360862000\"",
   "id": "20220415_60o30d1pcoo30c1g60o30dr56o",
   "status": "confirmed",
   "htmlLink": "https://www.google.com/calendar/event?eid=MjAyMjA0MTVfNjBvMzBkMXBjb28zMGMxZzYwbzMwZHI1Nm8gaWQuaW5kb25lc2lhbiNob2xpZGF5QHY",
   "created": "2021-01-09T19:06:20.000Z",
   "updated": "2021-01-09T19:06:20.431Z",
   "summary": "Wafat Isa Almasih",
   "creator": {
    "email": "id.indonesian#holiday@group.v.calendar.google.com",
    "displayName": "Hari libur di Indonesia",
    "self": true
   },
   "organizer": {
    "email": "id.indonesian#holiday@group.v.calendar.google.com",
    "displayName": "Hari libur di Indonesia",
    "self": true
   },
   "start": {
    "date": "2022-04-15"
   },
   "end": {
    "date": "2022-04-16"
   },
   "transparency": "transparent",
   "visibility": "public",
   "iCalUID": "20220415_60o30d1pcoo30c1g60o30dr56o@google.com",
   "sequence": 0,
   "eventType": "default"
  },
  {
   "kind": "calendar#event",
   "etag": "\"3220438360862000\"",
   "id": "20220417_60o30d3160o30c1g60o30dr56o",
   "status": "confirmed",
   "htmlLink": "https://www.google.com/calendar/event?eid=MjAyMjA0MTdfNjBvMzBkMzE2MG8zMGMxZzYwbzMwZHI1Nm8gaWQuaW5kb25lc2lhbiNob2xpZGF5QHY",
   "created": "2021-01-09T19:06:20.000Z",
   "updated": "2021-01-09T19:06:20.431Z",
   "summary": "Hari Paskah",
   "creator": {
    "email": "id.indonesian#holiday@group.v.calendar.google.com",
    "displayName": "Hari libur di Indonesia",
    "self": true
   },
   "organizer": {
    "email": "id.indonesian#holiday@group.v.calendar.google.com",
    "displayName": "Hari libur di Indonesia",
    "self": true
   },
   "start": {
    "date": "2022-04-17"
   },
   "end": {
    "date": "2022-04-18"
   },
   "transparency": "transparent",
   "visibility": "public",
   "iCalUID": "20220417_60o30d3160o30c1g60o30dr56o@google.com",
   "sequence": 0,
   "eventType": "default"
  },
  {
   "kind": "calendar#event",
   "etag": "\"3220438360862000\"",
   "id": "20220501_60o30o9j74o30c1g60o30dr56o",
   "status": "confirmed",
   "htmlLink": "https://www.google.com/calendar/event?eid=MjAyMjA1MDFfNjBvMzBvOWo3NG8zMGMxZzYwbzMwZHI1Nm8gaWQuaW5kb25lc2lhbiNob2xpZGF5QHY",
   "created": "2021-01-09T19:06:20.000Z",
   "updated": "2021-01-09T19:06:20.431Z",
   "summary": "Hari Buruh Internasional/Pekerja",
   "creator": {
    "email": "id.indonesian#holiday@group.v.calendar.google.com",
    "displayName": "Hari libur di Indonesia",
    "self": true
   },
   "organizer": {
    "email": "id.indonesian#holiday@group.v.calendar.google.com",
    "displayName": "Hari libur di Indonesia",
    "self": true
   },
   "start": {
    "date": "2022-05-01"
   },
   "end": {
    "date": "2022-05-02"
   },
   "transparency": "transparent",
   "visibility": "public",
   "iCalUID": "20220501_60o30o9j74o30c1g60o30dr56o@google.com",
   "sequence": 0,
   "eventType": "default"
  },
  {
   "kind": "calendar#event",
   "etag": "\"3220438360862000\"",
   "id": "20220503_60o32ob4c4o30c1g60o30db16c",
   "status": "confirmed",
   "htmlLink": "https://www.google.com/calendar/event?eid=MjAyMjA1MDNfNjBvMzJvYjRjNG8zMGMxZzYwbzMwZGIxNmMgaWQuaW5kb25lc2lhbiNob2xpZGF5QHY",
   "created": "2021-01-09T19:06:20.000Z",
   "updated": "2021-01-09T19:06:20.431Z",
   "summary": "Idul Fitri (Lebaran Mudik)",
   "creator": {
    "email": "id.indonesian#holiday@group.v.calendar.google.com",
    "displayName": "Hari libur di Indonesia",
    "self": true
   },
   "organizer": {
    "email": "id.indonesian#holiday@group.v.calendar.google.com",
    "displayName": "Hari libur di Indonesia",
    "self": true
   },
   "start": {
    "date": "2022-05-03"
   },
   "end": {
    "date": "2022-05-04"
   },
   "transparency": "transparent",
   "visibility": "public",
   "iCalUID": "20220503_60o32ob4c4o30c1g60o30db16c@google.com",
   "sequence": 0,
   "eventType": "default"
  },
  {
   "kind": "calendar#event",
   "etag": "\"3220438360862000\"",
   "id": "20220504_60o30d316ko30c1g60o30db16c",
   "status": "confirmed",
   "htmlLink": "https://www.google.com/calendar/event?eid=MjAyMjA1MDRfNjBvMzBkMzE2a28zMGMxZzYwbzMwZGIxNmMgaWQuaW5kb25lc2lhbiNob2xpZGF5QHY",
   "created": "2021-01-09T19:06:20.000Z",
   "updated": "2021-01-09T19:06:20.431Z",
   "summary": "Idul Fitri (Lebaran Mudik)",
   "creator": {
    "email": "id.indonesian#holiday@group.v.calendar.google.com",
    "displayName": "Hari libur di Indonesia",
    "self": true
   },
   "organizer": {
    "email": "id.indonesian#holiday@group.v.calendar.google.com",
    "displayName": "Hari libur di Indonesia",
    "self": true
   },
   "start": {
    "date": "2022-05-04"
   },
   "end": {
    "date": "2022-05-05"
   },
   "transparency": "transparent",
   "visibility": "public",
   "iCalUID": "20220504_60o30d316ko30c1g60o30db16c@google.com",
   "sequence": 0,
   "eventType": "default"
  },
  {
   "kind": "calendar#event",
   "etag": "\"3220438360862000\"",
   "id": "20220526_60o30d31cko30c1g60o30dr56o",
   "status": "confirmed",
   "htmlLink": "https://www.google.com/calendar/event?eid=MjAyMjA1MjZfNjBvMzBkMzFja28zMGMxZzYwbzMwZHI1Nm8gaWQuaW5kb25lc2lhbiNob2xpZGF5QHY",
   "created": "2021-01-09T19:06:20.000Z",
   "updated": "2021-01-09T19:06:20.431Z",
   "summary": "Kenaikan Yesus Kristus",
   "creator": {
    "email": "id.indonesian#holiday@group.v.calendar.google.com",
    "displayName": "Hari libur di Indonesia",
    "self": true
   },
   "organizer": {
    "email": "id.indonesian#holiday@group.v.calendar.google.com",
    "displayName": "Hari libur di Indonesia",
    "self": true
   },
   "start": {
    "date": "2022-05-26"
   },
   "end": {
    "date": "2022-05-27"
   },
   "transparency": "transparent",
   "visibility": "public",
   "iCalUID": "20220526_60o30d31cko30c1g60o30dr56o@google.com",
   "sequence": 0,
   "eventType": "default"
  },
  {
   "kind": "calendar#event",
   "etag": "\"3220438360862000\"",
   "id": "20220601_60o32dpn70o30c1g60o30dr56o",
   "status": "confirmed",
   "htmlLink": "https://www.google.com/calendar/event?eid=MjAyMjA2MDFfNjBvMzJkcG43MG8zMGMxZzYwbzMwZHI1Nm8gaWQuaW5kb25lc2lhbiNob2xpZGF5QHY",
   "created": "2021-01-09T19:06:20.000Z",
   "updated": "2021-01-09T19:06:20.431Z",
   "summary": "Hari Lahir Pancasila",
   "creator": {
    "email": "id.indonesian#holiday@group.v.calendar.google.com",
    "displayName": "Hari libur di Indonesia",
    "self": true
   },
   "organizer": {
    "email": "id.indonesian#holiday@group.v.calendar.google.com",
    "displayName": "Hari libur di Indonesia",
    "self": true
   },
   "start": {
    "date": "2022-06-01"
   },
   "end": {
    "date": "2022-06-02"
   },
   "transparency": "transparent",
   "visibility": "public",
   "iCalUID": "20220601_60o32dpn70o30c1g60o30dr56o@google.com",
   "sequence": 0,
   "eventType": "default"
  },
  {
   "kind": "calendar#event",
   "etag": "\"3220438360862000\"",
   "id": "20220710_60o30d31c8o30c1g60o30db16c",
   "status": "confirmed",
   "htmlLink": "https://www.google.com/calendar/event?eid=MjAyMjA3MTBfNjBvMzBkMzFjOG8zMGMxZzYwbzMwZGIxNmMgaWQuaW5kb25lc2lhbiNob2xpZGF5QHY",
   "created": "2021-01-09T19:06:20.000Z",
   "updated": "2021-01-09T19:06:20.431Z",
   "summary": "Idul Adha (Lebaran Haji)",
   "creator": {
    "email": "id.indonesian#holiday@group.v.calendar.google.com",
    "displayName": "Hari libur di Indonesia",
    "self": true
   },
   "organizer": {
    "email": "id.indonesian#holiday@group.v.calendar.google.com",
    "displayName": "Hari libur di Indonesia",
    "self": true
   },
   "start": {
    "date": "2022-07-10"
   },
   "end": {
    "date": "2022-07-11"
   },
   "transparency": "transparent",
   "visibility": "public",
   "iCalUID": "20220710_60o30d31c8o30c1g60o30db16c@google.com",
   "sequence": 0,
   "eventType": "default"
  },
  {
   "kind": "calendar#event",
   "etag": "\"3220438360862000\"",
   "id": "20220730_60o30d3260o30c1g60o30db16g",
   "status": "confirmed",
   "htmlLink": "https://www.google.com/calendar/event?eid=MjAyMjA3MzBfNjBvMzBkMzI2MG8zMGMxZzYwbzMwZGIxNmcgaWQuaW5kb25lc2lhbiNob2xpZGF5QHY",
   "created": "2021-01-09T19:06:20.000Z",
   "updated": "2021-01-09T19:06:20.431Z",
   "summary": "Satu Muharam/Tahun Baru Hijriyah",
   "creator": {
    "email": "id.indonesian#holiday@group.v.calendar.google.com",
    "displayName": "Hari libur di Indonesia",
    "self": true
   },
   "organizer": {
    "email": "id.indonesian#holiday@group.v.calendar.google.com",
    "displayName": "Hari libur di Indonesia",
    "self": true
   },
   "start": {
    "date": "2022-07-30"
   },
   "end": {
    "date": "2022-07-31"
   },
   "transparency": "transparent",
   "visibility": "public",
   "iCalUID": "20220730_60o30d3260o30c1g60o30db16g@google.com",
   "sequence": 0,
   "eventType": "default"
  },
  {
   "kind": "calendar#event",
   "etag": "\"3220438360862000\"",
   "id": "20220817_60o30d326co30c1g60o30dr56o",
   "status": "confirmed",
   "htmlLink": "https://www.google.com/calendar/event?eid=MjAyMjA4MTdfNjBvMzBkMzI2Y28zMGMxZzYwbzMwZHI1Nm8gaWQuaW5kb25lc2lhbiNob2xpZGF5QHY",
   "created": "2021-01-09T19:06:20.000Z",
   "updated": "2021-01-09T19:06:20.431Z",
   "summary": "Hari Proklamasi Kemerdekaan R.I.",
   "creator": {
    "email": "id.indonesian#holiday@group.v.calendar.google.com",
    "displayName": "Hari libur di Indonesia",
    "self": true
   },
   "organizer": {
    "email": "id.indonesian#holiday@group.v.calendar.google.com",
    "displayName": "Hari libur di Indonesia",
    "self": true
   },
   "start": {
    "date": "2022-08-17"
   },
   "end": {
    "date": "2022-08-18"
   },
   "transparency": "transparent",
   "visibility": "public",
   "iCalUID": "20220817_60o30d326co30c1g60o30dr56o@google.com",
   "sequence": 0,
   "eventType": "default"
  },
  {
   "kind": "calendar#event",
   "etag": "\"3220438360862000\"",
   "id": "20221008_60o30d3268o30c1g60o30db16g",
   "status": "confirmed",
   "htmlLink": "https://www.google.com/calendar/event?eid=MjAyMjEwMDhfNjBvMzBkMzI2OG8zMGMxZzYwbzMwZGIxNmcgaWQuaW5kb25lc2lhbiNob2xpZGF5QHY",
   "created": "2021-01-09T19:06:20.000Z",
   "updated": "2021-01-09T19:06:20.431Z",
   "summary": "Maulid Nabi Muhammad",
   "creator": {
    "email": "id.indonesian#holiday@group.v.calendar.google.com",
    "displayName": "Hari libur di Indonesia",
    "self": true
   },
   "organizer": {
    "email": "id.indonesian#holiday@group.v.calendar.google.com",
    "displayName": "Hari libur di Indonesia",
    "self": true
   },
   "start": {
    "date": "2022-10-08"
   },
   "end": {
    "date": "2022-10-09"
   },
   "transparency": "transparent",
   "visibility": "public",
   "iCalUID": "20221008_60o30d3268o30c1g60o30db16g@google.com",
   "sequence": 0,
   "eventType": "default"
  },
  {
   "kind": "calendar#event",
   "etag": "\"3220438360862000\"",
   "id": "20221024_60o30p1nc4o30c1g60o30dr56o",
   "status": "confirmed",
   "htmlLink": "https://www.google.com/calendar/event?eid=MjAyMjEwMjRfNjBvMzBwMW5jNG8zMGMxZzYwbzMwZHI1Nm8gaWQuaW5kb25lc2lhbiNob2xpZGF5QHY",
   "created": "2021-01-09T19:06:20.000Z",
   "updated": "2021-01-09T19:06:20.431Z",
   "summary": "Diwali/Deepavali",
   "creator": {
    "email": "id.indonesian#holiday@group.v.calendar.google.com",
    "displayName": "Hari libur di Indonesia",
    "self": true
   },
   "organizer": {
    "email": "id.indonesian#holiday@group.v.calendar.google.com",
    "displayName": "Hari libur di Indonesia",
    "self": true
   },
   "start": {
    "date": "2022-10-24"
   },
   "end": {
    "date": "2022-10-25"
   },
   "transparency": "transparent",
   "visibility": "public",
   "iCalUID": "20221024_60o30p1nc4o30c1g60o30dr56o@google.com",
   "sequence": 0,
   "eventType": "default"
  },
  {
   "kind": "calendar#event",
   "etag": "\"3220438360862000\"",
   "id": "20221224_60o30d3168o32c1g60o30dr56o",
   "status": "confirmed",
   "htmlLink": "https://www.google.com/calendar/event?eid=MjAyMjEyMjRfNjBvMzBkMzE2OG8zMmMxZzYwbzMwZHI1Nm8gaWQuaW5kb25lc2lhbiNob2xpZGF5QHY",
   "created": "2021-01-09T19:06:20.000Z",
   "updated": "2021-01-09T19:06:20.431Z",
   "summary": "Malam Natal",
   "creator": {
    "email": "id.indonesian#holiday@group.v.calendar.google.com",
    "displayName": "Hari libur di Indonesia",
    "self": true
   },
   "organizer": {
    "email": "id.indonesian#holiday@group.v.calendar.google.com",
    "displayName": "Hari libur di Indonesia",
    "self": true
   },
   "start": {
    "date": "2022-12-24"
   },
   "end": {
    "date": "2022-12-25"
   },
   "transparency": "transparent",
   "visibility": "public",
   "iCalUID": "20221224_60o30d3168o32c1g60o30dr56o@google.com",
   "sequence": 0,
   "eventType": "default"
  },
  {
   "kind": "calendar#event",
   "etag": "\"3220438360862000\"",
   "id": "20221225_60o30d316co30c1g60o30dr56o",
   "status": "confirmed",
   "htmlLink": "https://www.google.com/calendar/event?eid=MjAyMjEyMjVfNjBvMzBkMzE2Y28zMGMxZzYwbzMwZHI1Nm8gaWQuaW5kb25lc2lhbiNob2xpZGF5QHY",
   "created": "2021-01-09T19:06:20.000Z",
   "updated": "2021-01-09T19:06:20.431Z",
   "summary": "Hari Natal",
   "creator": {
    "email": "id.indonesian#holiday@group.v.calendar.google.com",
    "displayName": "Hari libur di Indonesia",
    "self": true
   },
   "organizer": {
    "email": "id.indonesian#holiday@group.v.calendar.google.com",
    "displayName": "Hari libur di Indonesia",
    "self": true
   },
   "start": {
    "date": "2022-12-25"
   },
   "end": {
    "date": "2022-12-26"
   },
   "transparency": "transparent",
   "visibility": "public",
   "iCalUID": "20221225_60o30d316co30c1g60o30dr56o@google.com",
   "sequence": 0,
   "eventType": "default"
  },
  {
   "kind": "calendar#event",
   "etag": "\"3220438360862000\"",
   "id": "20221231_60o30d1pcco30c1g60o30dr56o",
   "status": "confirmed",
   "htmlLink": "https://www.google.com/calendar/event?eid=MjAyMjEyMzFfNjBvMzBkMXBjY28zMGMxZzYwbzMwZHI1Nm8gaWQuaW5kb25lc2lhbiNob2xpZGF5QHY",
   "created": "2021-01-09T19:06:20.000Z",
   "updated": "2021-01-09T19:06:20.431Z",
   "summary": "Malam Tahun Baru",
   "creator": {
    "email": "id.indonesian#holiday@group.v.calendar.google.com",
    "displayName": "Hari libur di Indonesia",
    "self": true
   },
   "organizer": {
    "email": "id.indonesian#holiday@group.v.calendar.google.com",
    "displayName": "Hari libur di Indonesia",
    "self": true
   },
   "start": {
    "date": "2022-12-31"
   },
   "end": {
    "date": "2023-01-01"
   },
   "transparency": "transparent",
   "visibility": "public",
   "iCalUID": "20221231_60o30d1pcco30c1g60o30dr56o@google.com",
   "sequence": 0,
   "eventType": "default"
  },
  {
   "kind": "calendar#event",
   "etag": "\"3229011686458000\"",
   "id": "20201209_60o32e9lc4o30c1g60o30dr56g",
   "status": "confirmed",
   "htmlLink": "https://www.google.com/calendar/event?eid=MjAyMDEyMDlfNjBvMzJlOWxjNG8zMGMxZzYwbzMwZHI1NmcgaWQuaW5kb25lc2lhbiNob2xpZGF5QHY",
   "created": "2021-02-28T09:50:43.000Z",
   "updated": "2021-02-28T09:50:43.229Z",
   "summary": "Election Day",
   "creator": {
    "email": "id.indonesian#holiday@group.v.calendar.google.com",
    "displayName": "Hari libur di Indonesia",
    "self": true
   },
   "organizer": {
    "email": "id.indonesian#holiday@group.v.calendar.google.com",
    "displayName": "Hari libur di Indonesia",
    "self": true
   },
   "start": {
    "date": "2020-12-09"
   },
   "end": {
    "date": "2020-12-10"
   },
   "transparency": "transparent",
   "visibility": "public",
   "iCalUID": "20201209_60o32e9lc4o30c1g60o30dr56g@google.com",
   "sequence": 0,
   "eventType": "default"
  }
 ]
}
